{
    "$schema": "https://schema.management.azure.com/schemas/2015-01-01/deploymentTemplate.json#",
    "contentVersion": "1.0.0.0",
    "parameters": {
        "virtualMachines_windows_01_name": {
            "defaultValue": "windows-01",
            "type": "String"
        },
        "virtualMachines_ubuntuvm_01_name": {
            "defaultValue": "ubuntuvm-01",
            "type": "String"
        },
        "virtualMachines_kali_linuxvm01_name": {
            "defaultValue": "kali-linuxvm01",
            "type": "String"
        },
        "networkInterfaces_windows_01371_name": {
            "defaultValue": "windows-01371",
            "type": "String"
        },
        "networkInterfaces_ubuntuvm_01949_name": {
            "defaultValue": "ubuntuvm-01949",
            "type": "String"
        },
        "virtualNetworks_inacap_demoRG_vnet_name": {
            "defaultValue": "inacap-demoRG-vnet",
            "type": "String"
        },
        "networkInterfaces_kali_linuxvm01840_name": {
            "defaultValue": "kali-linuxvm01840",
            "type": "String"
        },
        "publicIPAddresses_kali_linuxvm01_ip_name": {
            "defaultValue": "kali-linuxvm01-ip",
            "type": "String"
        },
        "networkSecurityGroups_windows_01_nsg_name": {
            "defaultValue": "windows-01-nsg",
            "type": "String"
        },
        "networkSecurityGroups_ubuntuvm_01_nsg_name": {
            "defaultValue": "ubuntuvm-01-nsg",
            "type": "String"
        },
        "networkSecurityGroups_kali_linuxvm01_nsg_name": {
            "defaultValue": "kali-linuxvm01-nsg",
            "type": "String"
        },
        "subnets_default_name": {
            "defaultValue": "default",
            "type": "String"
        },
        "securityRules_SSH_name": {
            "defaultValue": "SSH",
            "type": "String"
        },
        "securityRules_RDP_name": {
            "defaultValue": "RDP",
            "type": "String"
        },
        "virtualMachines_kali_linuxvm01_id": {
            "defaultValue": "/subscriptions/979226a0-fd4a-4f1b-9bc5-46d431e71647/resourceGroups/inacap-demoRG/providers/Microsoft.Compute/disks/kali-linuxvm01_OsDisk_1_7d8a01bf7a4f4638ad50a2d33cd138f5",
            "type": "String"
        },
        "virtualMachines_ubuntuvm_01_id": {
            "defaultValue": "/subscriptions/979226a0-fd4a-4f1b-9bc5-46d431e71647/resourceGroups/inacap-demoRG/providers/Microsoft.Compute/disks/ubuntuvm-01_OsDisk_1_efa256016bf24e3c9ce61120aaf35a19",
            "type": "String"
        },
        "virtualMachines_windows_01_id": {
            "defaultValue": "/subscriptions/979226a0-fd4a-4f1b-9bc5-46d431e71647/resourceGroups/inacap-demoRG/providers/Microsoft.Compute/disks/windows-01_OsDisk_1_2c824d749fe44d01b80b4893c53a9839",
            "type": "String"
        }
    },
    "variables": {},
    "resources": [
        {
            "comments": "Generalized from resource: '/subscriptions/979226a0-fd4a-4f1b-9bc5-46d431e71647/resourceGroups/inacap-demoRG/providers/Microsoft.Compute/virtualMachines/kali-linuxvm01'.",
            "type": "Microsoft.Compute/virtualMachines",
            "name": "[parameters('virtualMachines_kali_linuxvm01_name')]",
            "apiVersion": "2018-06-01",
            "location": "brazilsouth",
            "plan": {
                "name": "kali",
                "product": "kali-linux",
                "publisher": "kali-linux"
            },
            "tags": {},
            "scale": null,
            "properties": {
                "hardwareProfile": {
                    "vmSize": "Standard_B2s"
                },
                "storageProfile": {
                    "imageReference": {
                        "publisher": "kali-linux",
                        "offer": "kali-linux",
                        "sku": "kali",
                        "version": "2018.4.0"
                    },
                    "osDisk": {
                        "osType": "Linux",
                        "name": "[concat(parameters('virtualMachines_kali_linuxvm01_name'),'_OsDisk_1_7d8a01bf7a4f4638ad50a2d33cd138f5')]",
                        "createOption": "FromImage",
                        "caching": "ReadWrite",
                        "managedDisk": {
                            "storageAccountType": "Premium_LRS",
                            "id": "[parameters('virtualMachines_kali_linuxvm01_id')]"
                        },
                        "diskSizeGB": 30
                    },
                    "dataDisks": []
                },
                "osProfile": {
                    "computerName": "[parameters('virtualMachines_kali_linuxvm01_name')]",
                    "adminUsername": "benjadiaz",
                    "linuxConfiguration": {
                        "disablePasswordAuthentication": false,
                        "provisionVMAgent": true
                    },
                    "secrets": [],
                    "allowExtensionOperations": true
                },
                "networkProfile": {
                    "networkInterfaces": [
                        {
                            "id": "[resourceId('Microsoft.Network/networkInterfaces', parameters('networkInterfaces_kali_linuxvm01840_name'))]"
                        }
                    ]
                },
                "diagnosticsProfile": {
                    "bootDiagnostics": {
                        "enabled": true,
                        "storageUri": "https://inacapdemorgdiag.blob.core.windows.net/"
                    }
                }
            },
            "dependsOn": [
                "[resourceId('Microsoft.Network/networkInterfaces', parameters('networkInterfaces_kali_linuxvm01840_name'))]"
            ]
        },
        {
            "comments": "Generalized from resource: '/subscriptions/979226a0-fd4a-4f1b-9bc5-46d431e71647/resourceGroups/inacap-demoRG/providers/Microsoft.Compute/virtualMachines/ubuntuvm-01'.",
            "type": "Microsoft.Compute/virtualMachines",
            "name": "[parameters('virtualMachines_ubuntuvm_01_name')]",
            "apiVersion": "2018-06-01",
            "location": "brazilsouth",
            "tags": {},
            "scale": null,
            "properties": {
                "hardwareProfile": {
                    "vmSize": "Standard_D2s_v3"
                },
                "storageProfile": {
                    "imageReference": {
                        "publisher": "Canonical",
                        "offer": "UbuntuServer",
                        "sku": "16.04-LTS",
                        "version": "latest"
                    },
                    "osDisk": {
                        "osType": "Linux",
                        "name": "[concat(parameters('virtualMachines_ubuntuvm_01_name'),'_OsDisk_1_efa256016bf24e3c9ce61120aaf35a19')]",
                        "createOption": "FromImage",
                        "caching": "ReadWrite",
                        "managedDisk": {
                            "storageAccountType": "Premium_LRS",
                            "id": "[parameters('virtualMachines_ubuntuvm_01_id')]"
                        },
                        "diskSizeGB": 30
                    },
                    "dataDisks": []
                },
                "osProfile": {
                    "computerName": "[parameters('virtualMachines_ubuntuvm_01_name')]",
                    "adminUsername": "benjadiaz",
                    "linuxConfiguration": {
                        "disablePasswordAuthentication": false,
                        "provisionVMAgent": true
                    },
                    "secrets": [],
                    "allowExtensionOperations": true
                },
                "networkProfile": {
                    "networkInterfaces": [
                        {
                            "id": "[resourceId('Microsoft.Network/networkInterfaces', parameters('networkInterfaces_ubuntuvm_01949_name'))]"
                        }
                    ]
                },
                "diagnosticsProfile": {
                    "bootDiagnostics": {
                        "enabled": true,
                        "storageUri": "https://inacapdemorgdiag.blob.core.windows.net/"
                    }
                }
            },
            "dependsOn": [
                "[resourceId('Microsoft.Network/networkInterfaces', parameters('networkInterfaces_ubuntuvm_01949_name'))]"
            ]
        },
        {
            "comments": "Generalized from resource: '/subscriptions/979226a0-fd4a-4f1b-9bc5-46d431e71647/resourceGroups/inacap-demoRG/providers/Microsoft.Compute/virtualMachines/windows-01'.",
            "type": "Microsoft.Compute/virtualMachines",
            "name": "[parameters('virtualMachines_windows_01_name')]",
            "apiVersion": "2018-06-01",
            "location": "brazilsouth",
            "tags": {},
            "scale": null,
            "properties": {
                "hardwareProfile": {
                    "vmSize": "Standard_DS2_v2"
                },
                "storageProfile": {
                    "imageReference": {
                        "publisher": "MicrosoftWindowsDesktop",
                        "offer": "Windows-10",
                        "sku": "rs4-pro",
                        "version": "latest"
                    },
                    "osDisk": {
                        "osType": "Windows",
                        "name": "[concat(parameters('virtualMachines_windows_01_name'),'_OsDisk_1_2c824d749fe44d01b80b4893c53a9839')]",
                        "createOption": "FromImage",
                        "caching": "ReadWrite",
                        "managedDisk": {
                            "storageAccountType": "Premium_LRS",
                            "id": "[parameters('virtualMachines_windows_01_id')]"
                        },
                        "diskSizeGB": 127
                    },
                    "dataDisks": []
                },
                "osProfile": {
                    "computerName": "[parameters('virtualMachines_windows_01_name')]",
                    "adminUsername": "benjadiaz",
                    "windowsConfiguration": {
                        "provisionVMAgent": true,
                        "enableAutomaticUpdates": true
                    },
                    "secrets": [],
                    "allowExtensionOperations": true
                },
                "networkProfile": {
                    "networkInterfaces": [
                        {
                            "id": "[resourceId('Microsoft.Network/networkInterfaces', parameters('networkInterfaces_windows_01371_name'))]"
                        }
                    ]
                },
                "diagnosticsProfile": {
                    "bootDiagnostics": {
                        "enabled": true,
                        "storageUri": "https://inacapdemorgdiag.blob.core.windows.net/"
                    }
                },
                "licenseType": "Windows_Client"
            },
            "dependsOn": [
                "[resourceId('Microsoft.Network/networkInterfaces', parameters('networkInterfaces_windows_01371_name'))]"
            ]
        },
        {
            "comments": "Generalized from resource: '/subscriptions/979226a0-fd4a-4f1b-9bc5-46d431e71647/resourceGroups/inacap-demoRG/providers/Microsoft.Network/networkInterfaces/kali-linuxvm01840'.",
            "type": "Microsoft.Network/networkInterfaces",
            "name": "[parameters('networkInterfaces_kali_linuxvm01840_name')]",
            "apiVersion": "2018-08-01",
            "location": "brazilsouth",
            "tags": {},
            "scale": null,
            "properties": {
                "provisioningState": "Succeeded",
                "resourceGuid": "b066886a-bc87-4778-9a93-1c56dfc22b32",
                "ipConfigurations": [
                    {
                        "name": "ipconfig1",
                        "etag": "W/\"9b4c12ae-1f3f-4986-980f-48a81c771af2\"",
                        "properties": {
                            "provisioningState": "Succeeded",
                            "privateIPAddress": "10.0.0.4",
                            "privateIPAllocationMethod": "Dynamic",
                            "publicIPAddress": {
                                "id": "[resourceId('Microsoft.Network/publicIPAddresses', parameters('publicIPAddresses_kali_linuxvm01_ip_name'))]"
                            },
                            "subnet": {
                                "id": "[resourceId('Microsoft.Network/virtualNetworks/subnets', parameters('virtualNetworks_inacap_demoRG_vnet_name'), parameters('subnets_default_name'))]"
                            },
                            "primary": true,
                            "privateIPAddressVersion": "IPv4"
                        }
                    }
                ],
                "dnsSettings": {
                    "dnsServers": [],
                    "appliedDnsServers": [],
                    "internalDomainNameSuffix": "dymlq5syoote5ht03bxrir44ah.nx.internal.cloudapp.net"
                },
                "macAddress": "00-0D-3A-C0-6F-03",
                "enableAcceleratedNetworking": false,
                "enableIPForwarding": false,
                "networkSecurityGroup": {
                    "id": "[resourceId('Microsoft.Network/networkSecurityGroups', parameters('networkSecurityGroups_kali_linuxvm01_nsg_name'))]"
                },
                "primary": true,
                "tapConfigurations": []
            },
            "dependsOn": [
                "[resourceId('Microsoft.Network/publicIPAddresses', parameters('publicIPAddresses_kali_linuxvm01_ip_name'))]",
                "[resourceId('Microsoft.Network/virtualNetworks/subnets', parameters('virtualNetworks_inacap_demoRG_vnet_name'), parameters('subnets_default_name'))]",
                "[resourceId('Microsoft.Network/networkSecurityGroups', parameters('networkSecurityGroups_kali_linuxvm01_nsg_name'))]"
            ]
        },
        {
            "comments": "Generalized from resource: '/subscriptions/979226a0-fd4a-4f1b-9bc5-46d431e71647/resourceGroups/inacap-demoRG/providers/Microsoft.Network/networkInterfaces/ubuntuvm-01949'.",
            "type": "Microsoft.Network/networkInterfaces",
            "name": "[parameters('networkInterfaces_ubuntuvm_01949_name')]",
            "apiVersion": "2018-08-01",
            "location": "brazilsouth",
            "tags": {},
            "scale": null,
            "properties": {
                "provisioningState": "Succeeded",
                "resourceGuid": "8eda0473-9c8e-4ea4-a2c9-b6e6d5e9b070",
                "ipConfigurations": [
                    {
                        "name": "ipconfig1",
                        "etag": "W/\"a4a3ece7-7780-48d0-8d2a-7eda7f919c00\"",
                        "properties": {
                            "provisioningState": "Succeeded",
                            "privateIPAddress": "10.0.0.6",
                            "privateIPAllocationMethod": "Dynamic",
                            "subnet": {
                                "id": "[resourceId('Microsoft.Network/virtualNetworks/subnets', parameters('virtualNetworks_inacap_demoRG_vnet_name'), parameters('subnets_default_name'))]"
                            },
                            "primary": true,
                            "privateIPAddressVersion": "IPv4"
                        }
                    }
                ],
                "dnsSettings": {
                    "dnsServers": [],
                    "appliedDnsServers": [],
                    "internalDomainNameSuffix": "dymlq5syoote5ht03bxrir44ah.nx.internal.cloudapp.net"
                },
                "macAddress": "00-0D-3A-C1-52-EB",
                "enableAcceleratedNetworking": false,
                "enableIPForwarding": false,
                "networkSecurityGroup": {
                    "id": "[resourceId('Microsoft.Network/networkSecurityGroups', parameters('networkSecurityGroups_ubuntuvm_01_nsg_name'))]"
                },
                "primary": true,
                "tapConfigurations": []
            },
            "dependsOn": [
                "[resourceId('Microsoft.Network/virtualNetworks/subnets', parameters('virtualNetworks_inacap_demoRG_vnet_name'), parameters('subnets_default_name'))]",
                "[resourceId('Microsoft.Network/networkSecurityGroups', parameters('networkSecurityGroups_ubuntuvm_01_nsg_name'))]"
            ]
        },
        {
            "comments": "Generalized from resource: '/subscriptions/979226a0-fd4a-4f1b-9bc5-46d431e71647/resourceGroups/inacap-demoRG/providers/Microsoft.Network/networkInterfaces/windows-01371'.",
            "type": "Microsoft.Network/networkInterfaces",
            "name": "[parameters('networkInterfaces_windows_01371_name')]",
            "apiVersion": "2018-08-01",
            "location": "brazilsouth",
            "tags": {},
            "scale": null,
            "properties": {
                "provisioningState": "Succeeded",
                "resourceGuid": "7e125d3d-3bbb-452c-b522-9f22c219f953",
                "ipConfigurations": [
                    {
                        "name": "ipconfig1",
                        "etag": "W/\"d7a3f4bb-2253-46f8-ab31-623e5027478e\"",
                        "properties": {
                            "provisioningState": "Succeeded",
                            "privateIPAddress": "10.0.0.5",
                            "privateIPAllocationMethod": "Dynamic",
                            "subnet": {
                                "id": "[resourceId('Microsoft.Network/virtualNetworks/subnets', parameters('virtualNetworks_inacap_demoRG_vnet_name'), parameters('subnets_default_name'))]"
                            },
                            "primary": true,
                            "privateIPAddressVersion": "IPv4"
                        }
                    }
                ],
                "dnsSettings": {
                    "dnsServers": [],
                    "appliedDnsServers": [],
                    "internalDomainNameSuffix": "dymlq5syoote5ht03bxrir44ah.nx.internal.cloudapp.net"
                },
                "macAddress": "00-0D-3A-C0-9F-BB",
                "enableAcceleratedNetworking": false,
                "enableIPForwarding": false,
                "networkSecurityGroup": {
                    "id": "[resourceId('Microsoft.Network/networkSecurityGroups', parameters('networkSecurityGroups_windows_01_nsg_name'))]"
                },
                "primary": true,
                "tapConfigurations": []
            },
            "dependsOn": [
                "[resourceId('Microsoft.Network/virtualNetworks/subnets', parameters('virtualNetworks_inacap_demoRG_vnet_name'), parameters('subnets_default_name'))]",
                "[resourceId('Microsoft.Network/networkSecurityGroups', parameters('networkSecurityGroups_windows_01_nsg_name'))]"
            ]
        },
        {
            "comments": "Generalized from resource: '/subscriptions/979226a0-fd4a-4f1b-9bc5-46d431e71647/resourceGroups/inacap-demoRG/providers/Microsoft.Network/networkSecurityGroups/kali-linuxvm01-nsg'.",
            "type": "Microsoft.Network/networkSecurityGroups",
            "name": "[parameters('networkSecurityGroups_kali_linuxvm01_nsg_name')]",
            "apiVersion": "2018-08-01",
            "location": "brazilsouth",
            "tags": {},
            "scale": null,
            "properties": {
                "provisioningState": "Succeeded",
                "resourceGuid": "cbfa704d-59c7-4364-aa14-9d0bf840085e",
                "securityRules": [
                    {
                        "name": "SSH",
                        "etag": "W/\"536ecb75-d6de-473c-96e1-a0cef427ad81\"",
                        "properties": {
                            "provisioningState": "Succeeded",
                            "protocol": "TCP",
                            "sourcePortRange": "*",
                            "destinationPortRange": "22",
                            "sourceAddressPrefix": "*",
                            "destinationAddressPrefix": "*",
                            "access": "Allow",
                            "priority": 300,
                            "direction": "Inbound",
                            "sourcePortRanges": [],
                            "destinationPortRanges": [],
                            "sourceAddressPrefixes": [],
                            "destinationAddressPrefixes": []
                        }
                    },
                    {
                        "name": "RDP",
                        "etag": "W/\"536ecb75-d6de-473c-96e1-a0cef427ad81\"",
                        "properties": {
                            "provisioningState": "Succeeded",
                            "protocol": "TCP",
                            "sourcePortRange": "*",
                            "destinationPortRange": "3389",
                            "sourceAddressPrefix": "*",
                            "destinationAddressPrefix": "*",
                            "access": "Allow",
                            "priority": 320,
                            "direction": "Inbound",
                            "sourcePortRanges": [],
                            "destinationPortRanges": [],
                            "sourceAddressPrefixes": [],
                            "destinationAddressPrefixes": []
                        }
                    }
                ],
                "defaultSecurityRules": [
                    {
                        "name": "AllowVnetInBound",
                        "etag": "W/\"536ecb75-d6de-473c-96e1-a0cef427ad81\"",
                        "properties": {
                            "provisioningState": "Succeeded",
                            "description": "Allow inbound traffic from all VMs in VNET",
                            "protocol": "*",
                            "sourcePortRange": "*",
                            "destinationPortRange": "*",
                            "sourceAddressPrefix": "VirtualNetwork",
                            "destinationAddressPrefix": "VirtualNetwork",
                            "access": "Allow",
                            "priority": 65000,
                            "direction": "Inbound",
                            "sourcePortRanges": [],
                            "destinationPortRanges": [],
                            "sourceAddressPrefixes": [],
                            "destinationAddressPrefixes": []
                        }
                    },
                    {
                        "name": "AllowAzureLoadBalancerInBound",
                        "etag": "W/\"536ecb75-d6de-473c-96e1-a0cef427ad81\"",
                        "properties": {
                            "provisioningState": "Succeeded",
                            "description": "Allow inbound traffic from azure load balancer",
                            "protocol": "*",
                            "sourcePortRange": "*",
                            "destinationPortRange": "*",
                            "sourceAddressPrefix": "AzureLoadBalancer",
                            "destinationAddressPrefix": "*",
                            "access": "Allow",
                            "priority": 65001,
                            "direction": "Inbound",
                            "sourcePortRanges": [],
                            "destinationPortRanges": [],
                            "sourceAddressPrefixes": [],
                            "destinationAddressPrefixes": []
                        }
                    },
                    {
                        "name": "DenyAllInBound",
                        "etag": "W/\"536ecb75-d6de-473c-96e1-a0cef427ad81\"",
                        "properties": {
                            "provisioningState": "Succeeded",
                            "description": "Deny all inbound traffic",
                            "protocol": "*",
                            "sourcePortRange": "*",
                            "destinationPortRange": "*",
                            "sourceAddressPrefix": "*",
                            "destinationAddressPrefix": "*",
                            "access": "Deny",
                            "priority": 65500,
                            "direction": "Inbound",
                            "sourcePortRanges": [],
                            "destinationPortRanges": [],
                            "sourceAddressPrefixes": [],
                            "destinationAddressPrefixes": []
                        }
                    },
                    {
                        "name": "AllowVnetOutBound",
                        "etag": "W/\"536ecb75-d6de-473c-96e1-a0cef427ad81\"",
                        "properties": {
                            "provisioningState": "Succeeded",
                            "description": "Allow outbound traffic from all VMs to all VMs in VNET",
                            "protocol": "*",
                            "sourcePortRange": "*",
                            "destinationPortRange": "*",
                            "sourceAddressPrefix": "VirtualNetwork",
                            "destinationAddressPrefix": "VirtualNetwork",
                            "access": "Allow",
                            "priority": 65000,
                            "direction": "Outbound",
                            "sourcePortRanges": [],
                            "destinationPortRanges": [],
                            "sourceAddressPrefixes": [],
                            "destinationAddressPrefixes": []
                        }
                    },
                    {
                        "name": "AllowInternetOutBound",
                        "etag": "W/\"536ecb75-d6de-473c-96e1-a0cef427ad81\"",
                        "properties": {
                            "provisioningState": "Succeeded",
                            "description": "Allow outbound traffic from all VMs to Internet",
                            "protocol": "*",
                            "sourcePortRange": "*",
                            "destinationPortRange": "*",
                            "sourceAddressPrefix": "*",
                            "destinationAddressPrefix": "Internet",
                            "access": "Allow",
                            "priority": 65001,
                            "direction": "Outbound",
                            "sourcePortRanges": [],
                            "destinationPortRanges": [],
                            "sourceAddressPrefixes": [],
                            "destinationAddressPrefixes": []
                        }
                    },
                    {
                        "name": "DenyAllOutBound",
                        "etag": "W/\"536ecb75-d6de-473c-96e1-a0cef427ad81\"",
                        "properties": {
                            "provisioningState": "Succeeded",
                            "description": "Deny all outbound traffic",
                            "protocol": "*",
                            "sourcePortRange": "*",
                            "destinationPortRange": "*",
                            "sourceAddressPrefix": "*",
                            "destinationAddressPrefix": "*",
                            "access": "Deny",
                            "priority": 65500,
                            "direction": "Outbound",
                            "sourcePortRanges": [],
                            "destinationPortRanges": [],
                            "sourceAddressPrefixes": [],
                            "destinationAddressPrefixes": []
                        }
                    }
                ]
            },
            "dependsOn": []
        },
        {
            "comments": "Generalized from resource: '/subscriptions/979226a0-fd4a-4f1b-9bc5-46d431e71647/resourceGroups/inacap-demoRG/providers/Microsoft.Network/networkSecurityGroups/ubuntuvm-01-nsg'.",
            "type": "Microsoft.Network/networkSecurityGroups",
            "name": "[parameters('networkSecurityGroups_ubuntuvm_01_nsg_name')]",
            "apiVersion": "2018-08-01",
            "location": "brazilsouth",
            "tags": {},
            "scale": null,
            "properties": {
                "provisioningState": "Succeeded",
                "resourceGuid": "5e699296-6c58-4eee-9fc7-28cd5ddfd996",
                "securityRules": [],
                "defaultSecurityRules": [
                    {
                        "name": "AllowVnetInBound",
                        "etag": "W/\"0424866b-b282-4054-a37d-1ec2f2167a4b\"",
                        "properties": {
                            "provisioningState": "Succeeded",
                            "description": "Allow inbound traffic from all VMs in VNET",
                            "protocol": "*",
                            "sourcePortRange": "*",
                            "destinationPortRange": "*",
                            "sourceAddressPrefix": "VirtualNetwork",
                            "destinationAddressPrefix": "VirtualNetwork",
                            "access": "Allow",
                            "priority": 65000,
                            "direction": "Inbound",
                            "sourcePortRanges": [],
                            "destinationPortRanges": [],
                            "sourceAddressPrefixes": [],
                            "destinationAddressPrefixes": []
                        }
                    },
                    {
                        "name": "AllowAzureLoadBalancerInBound",
                        "etag": "W/\"0424866b-b282-4054-a37d-1ec2f2167a4b\"",
                        "properties": {
                            "provisioningState": "Succeeded",
                            "description": "Allow inbound traffic from azure load balancer",
                            "protocol": "*",
                            "sourcePortRange": "*",
                            "destinationPortRange": "*",
                            "sourceAddressPrefix": "AzureLoadBalancer",
                            "destinationAddressPrefix": "*",
                            "access": "Allow",
                            "priority": 65001,
                            "direction": "Inbound",
                            "sourcePortRanges": [],
                            "destinationPortRanges": [],
                            "sourceAddressPrefixes": [],
                            "destinationAddressPrefixes": []
                        }
                    },
                    {
                        "name": "DenyAllInBound",
                        "etag": "W/\"0424866b-b282-4054-a37d-1ec2f2167a4b\"",
                        "properties": {
                            "provisioningState": "Succeeded",
                            "description": "Deny all inbound traffic",
                            "protocol": "*",
                            "sourcePortRange": "*",
                            "destinationPortRange": "*",
                            "sourceAddressPrefix": "*",
                            "destinationAddressPrefix": "*",
                            "access": "Deny",
                            "priority": 65500,
                            "direction": "Inbound",
                            "sourcePortRanges": [],
                            "destinationPortRanges": [],
                            "sourceAddressPrefixes": [],
                            "destinationAddressPrefixes": []
                        }
                    },
                    {
                        "name": "AllowVnetOutBound",
                        "etag": "W/\"0424866b-b282-4054-a37d-1ec2f2167a4b\"",
                        "properties": {
                            "provisioningState": "Succeeded",
                            "description": "Allow outbound traffic from all VMs to all VMs in VNET",
                            "protocol": "*",
                            "sourcePortRange": "*",
                            "destinationPortRange": "*",
                            "sourceAddressPrefix": "VirtualNetwork",
                            "destinationAddressPrefix": "VirtualNetwork",
                            "access": "Allow",
                            "priority": 65000,
                            "direction": "Outbound",
                            "sourcePortRanges": [],
                            "destinationPortRanges": [],
                            "sourceAddressPrefixes": [],
                            "destinationAddressPrefixes": []
                        }
                    },
                    {
                        "name": "AllowInternetOutBound",
                        "etag": "W/\"0424866b-b282-4054-a37d-1ec2f2167a4b\"",
                        "properties": {
                            "provisioningState": "Succeeded",
                            "description": "Allow outbound traffic from all VMs to Internet",
                            "protocol": "*",
                            "sourcePortRange": "*",
                            "destinationPortRange": "*",
                            "sourceAddressPrefix": "*",
                            "destinationAddressPrefix": "Internet",
                            "access": "Allow",
                            "priority": 65001,
                            "direction": "Outbound",
                            "sourcePortRanges": [],
                            "destinationPortRanges": [],
                            "sourceAddressPrefixes": [],
                            "destinationAddressPrefixes": []
                        }
                    },
                    {
                        "name": "DenyAllOutBound",
                        "etag": "W/\"0424866b-b282-4054-a37d-1ec2f2167a4b\"",
                        "properties": {
                            "provisioningState": "Succeeded",
                            "description": "Deny all outbound traffic",
                            "protocol": "*",
                            "sourcePortRange": "*",
                            "destinationPortRange": "*",
                            "sourceAddressPrefix": "*",
                            "destinationAddressPrefix": "*",
                            "access": "Deny",
                            "priority": 65500,
                            "direction": "Outbound",
                            "sourcePortRanges": [],
                            "destinationPortRanges": [],
                            "sourceAddressPrefixes": [],
                            "destinationAddressPrefixes": []
                        }
                    }
                ]
            },
            "dependsOn": []
        },
        {
            "comments": "Generalized from resource: '/subscriptions/979226a0-fd4a-4f1b-9bc5-46d431e71647/resourceGroups/inacap-demoRG/providers/Microsoft.Network/networkSecurityGroups/windows-01-nsg'.",
            "type": "Microsoft.Network/networkSecurityGroups",
            "name": "[parameters('networkSecurityGroups_windows_01_nsg_name')]",
            "apiVersion": "2018-08-01",
            "location": "brazilsouth",
            "tags": {},
            "scale": null,
            "properties": {
                "provisioningState": "Succeeded",
                "resourceGuid": "e265bf18-737f-46fd-9d3f-5893d4e303d9",
                "securityRules": [],
                "defaultSecurityRules": [
                    {
                        "name": "AllowVnetInBound",
                        "etag": "W/\"e0856fae-7fd9-4e7b-abe4-9c8cd6e70007\"",
                        "properties": {
                            "provisioningState": "Succeeded",
                            "description": "Allow inbound traffic from all VMs in VNET",
                            "protocol": "*",
                            "sourcePortRange": "*",
                            "destinationPortRange": "*",
                            "sourceAddressPrefix": "VirtualNetwork",
                            "destinationAddressPrefix": "VirtualNetwork",
                            "access": "Allow",
                            "priority": 65000,
                            "direction": "Inbound",
                            "sourcePortRanges": [],
                            "destinationPortRanges": [],
                            "sourceAddressPrefixes": [],
                            "destinationAddressPrefixes": []
                        }
                    },
                    {
                        "name": "AllowAzureLoadBalancerInBound",
                        "etag": "W/\"e0856fae-7fd9-4e7b-abe4-9c8cd6e70007\"",
                        "properties": {
                            "provisioningState": "Succeeded",
                            "description": "Allow inbound traffic from azure load balancer",
                            "protocol": "*",
                            "sourcePortRange": "*",
                            "destinationPortRange": "*",
                            "sourceAddressPrefix": "AzureLoadBalancer",
                            "destinationAddressPrefix": "*",
                            "access": "Allow",
                            "priority": 65001,
                            "direction": "Inbound",
                            "sourcePortRanges": [],
                            "destinationPortRanges": [],
                            "sourceAddressPrefixes": [],
                            "destinationAddressPrefixes": []
                        }
                    },
                    {
                        "name": "DenyAllInBound",
                        "etag": "W/\"e0856fae-7fd9-4e7b-abe4-9c8cd6e70007\"",
                        "properties": {
                            "provisioningState": "Succeeded",
                            "description": "Deny all inbound traffic",
                            "protocol": "*",
                            "sourcePortRange": "*",
                            "destinationPortRange": "*",
                            "sourceAddressPrefix": "*",
                            "destinationAddressPrefix": "*",
                            "access": "Deny",
                            "priority": 65500,
                            "direction": "Inbound",
                            "sourcePortRanges": [],
                            "destinationPortRanges": [],
                            "sourceAddressPrefixes": [],
                            "destinationAddressPrefixes": []
                        }
                    },
                    {
                        "name": "AllowVnetOutBound",
                        "etag": "W/\"e0856fae-7fd9-4e7b-abe4-9c8cd6e70007\"",
                        "properties": {
                            "provisioningState": "Succeeded",
                            "description": "Allow outbound traffic from all VMs to all VMs in VNET",
                            "protocol": "*",
                            "sourcePortRange": "*",
                            "destinationPortRange": "*",
                            "sourceAddressPrefix": "VirtualNetwork",
                            "destinationAddressPrefix": "VirtualNetwork",
                            "access": "Allow",
                            "priority": 65000,
                            "direction": "Outbound",
                            "sourcePortRanges": [],
                            "destinationPortRanges": [],
                            "sourceAddressPrefixes": [],
                            "destinationAddressPrefixes": []
                        }
                    },
                    {
                        "name": "AllowInternetOutBound",
                        "etag": "W/\"e0856fae-7fd9-4e7b-abe4-9c8cd6e70007\"",
                        "properties": {
                            "provisioningState": "Succeeded",
                            "description": "Allow outbound traffic from all VMs to Internet",
                            "protocol": "*",
                            "sourcePortRange": "*",
                            "destinationPortRange": "*",
                            "sourceAddressPrefix": "*",
                            "destinationAddressPrefix": "Internet",
                            "access": "Allow",
                            "priority": 65001,
                            "direction": "Outbound",
                            "sourcePortRanges": [],
                            "destinationPortRanges": [],
                            "sourceAddressPrefixes": [],
                            "destinationAddressPrefixes": []
                        }
                    },
                    {
                        "name": "DenyAllOutBound",
                        "etag": "W/\"e0856fae-7fd9-4e7b-abe4-9c8cd6e70007\"",
                        "properties": {
                            "provisioningState": "Succeeded",
                            "description": "Deny all outbound traffic",
                            "protocol": "*",
                            "sourcePortRange": "*",
                            "destinationPortRange": "*",
                            "sourceAddressPrefix": "*",
                            "destinationAddressPrefix": "*",
                            "access": "Deny",
                            "priority": 65500,
                            "direction": "Outbound",
                            "sourcePortRanges": [],
                            "destinationPortRanges": [],
                            "sourceAddressPrefixes": [],
                            "destinationAddressPrefixes": []
                        }
                    }
                ]
            },
            "dependsOn": []
        },
        {
            "comments": "Generalized from resource: '/subscriptions/979226a0-fd4a-4f1b-9bc5-46d431e71647/resourceGroups/inacap-demoRG/providers/Microsoft.Network/publicIPAddresses/kali-linuxvm01-ip'.",
            "type": "Microsoft.Network/publicIPAddresses",
            "sku": {
                "name": "Basic",
                "tier": "Regional"
            },
            "name": "[parameters('publicIPAddresses_kali_linuxvm01_ip_name')]",
            "apiVersion": "2018-08-01",
            "location": "brazilsouth",
            "tags": {},
            "scale": null,
            "properties": {
                "provisioningState": "Succeeded",
                "resourceGuid": "7b303ef2-c16b-4ab0-8b85-13c01877c198",
                "ipAddress": "191.237.252.78",
                "publicIPAddressVersion": "IPv4",
                "publicIPAllocationMethod": "Dynamic",
                "idleTimeoutInMinutes": 4,
                "ipTags": []
            },
            "dependsOn": []
        },
        {
            "comments": "Generalized from resource: '/subscriptions/979226a0-fd4a-4f1b-9bc5-46d431e71647/resourceGroups/inacap-demoRG/providers/Microsoft.Network/virtualNetworks/inacap-demoRG-vnet'.",
            "type": "Microsoft.Network/virtualNetworks",
            "name": "[parameters('virtualNetworks_inacap_demoRG_vnet_name')]",
            "apiVersion": "2018-08-01",
            "location": "brazilsouth",
            "tags": {},
            "scale": null,
            "properties": {
                "provisioningState": "Succeeded",
                "resourceGuid": "7eb8181e-7358-4fa6-9e7a-e86f1447de07",
                "addressSpace": {
                    "addressPrefixes": [
                        "10.0.0.0/24"
                    ]
                },
                "subnets": [
                    {
                        "name": "default",
                        "etag": "W/\"01bb949e-b1d4-4811-9f36-60e3abaa9aba\"",
                        "properties": {
                            "provisioningState": "Succeeded",
                            "addressPrefix": "10.0.0.0/24",
                            "delegations": []
                        }
                    }
                ],
                "virtualNetworkPeerings": [],
                "enableDdosProtection": false,
                "enableVmProtection": false
            },
            "dependsOn": []
        },
        {
            "comments": "Generalized from resource: '/subscriptions/979226a0-fd4a-4f1b-9bc5-46d431e71647/resourceGroups/inacap-demoRG/providers/Microsoft.Network/networkSecurityGroups/kali-linuxvm01-nsg/securityRules/SSH'.",
            "type": "Microsoft.Network/networkSecurityGroups/securityRules",
            "name": "[concat(parameters('networkSecurityGroups_kali_linuxvm01_nsg_name'), '/', parameters('securityRules_SSH_name'))]",
            "apiVersion": "2018-08-01",
            "scale": null,
            "properties": {
                "provisioningState": "Succeeded",
                "protocol": "TCP",
                "sourcePortRange": "*",
                "destinationPortRange": "22",
                "sourceAddressPrefix": "*",
                "destinationAddressPrefix": "*",
                "access": "Allow",
                "priority": 300,
                "direction": "Inbound",
                "sourcePortRanges": [],
                "destinationPortRanges": [],
                "sourceAddressPrefixes": [],
                "destinationAddressPrefixes": []
            },
            "dependsOn": [
                "[resourceId('Microsoft.Network/networkSecurityGroups', parameters('networkSecurityGroups_kali_linuxvm01_nsg_name'))]"
            ]
        },
        {
            "comments": "Generalized from resource: '/subscriptions/979226a0-fd4a-4f1b-9bc5-46d431e71647/resourceGroups/inacap-demoRG/providers/Microsoft.Network/networkSecurityGroups/kali-linuxvm01-nsg/securityRules/RDP'.",
            "type": "Microsoft.Network/networkSecurityGroups/securityRules",
            "name": "[concat(parameters('networkSecurityGroups_kali_linuxvm01_nsg_name'), '/', parameters('securityRules_RDP_name'))]",
            "apiVersion": "2018-08-01",
            "scale": null,
            "properties": {
                "provisioningState": "Succeeded",
                "protocol": "TCP",
                "sourcePortRange": "*",
                "destinationPortRange": "3389",
                "sourceAddressPrefix": "*",
                "destinationAddressPrefix": "*",
                "access": "Allow",
                "priority": 320,
                "direction": "Inbound",
                "sourcePortRanges": [],
                "destinationPortRanges": [],
                "sourceAddressPrefixes": [],
                "destinationAddressPrefixes": []
            },
            "dependsOn": [
                "[resourceId('Microsoft.Network/networkSecurityGroups', parameters('networkSecurityGroups_kali_linuxvm01_nsg_name'))]"
            ]
        },
        {
            "comments": "Generalized from resource: '/subscriptions/979226a0-fd4a-4f1b-9bc5-46d431e71647/resourceGroups/inacap-demoRG/providers/Microsoft.Network/virtualNetworks/inacap-demoRG-vnet/subnets/default'.",
            "type": "Microsoft.Network/virtualNetworks/subnets",
            "name": "[concat(parameters('virtualNetworks_inacap_demoRG_vnet_name'), '/', parameters('subnets_default_name'))]",
            "apiVersion": "2018-08-01",
            "scale": null,
            "properties": {
                "provisioningState": "Succeeded",
                "addressPrefix": "10.0.0.0/24",
                "delegations": []
            },
            "dependsOn": [
                "[resourceId('Microsoft.Network/virtualNetworks', parameters('virtualNetworks_inacap_demoRG_vnet_name'))]"
            ]
        }
    ]
}
